setup.py
tkPlus/__init__.py
tkPlus/functions.py
tkPlus/messagebox.py
tkPlus/window.py
tkPlus.egg-info/PKG-INFO
tkPlus.egg-info/SOURCES.txt
tkPlus.egg-info/dependency_links.txt
tkPlus.egg-info/top_level.txt