Metadata-Version: 1.1
Name: tkPlus
Version: 0.0.1
Summary: 若宇工作室tkinter扩展库
Home-page: https://github.com/
Author: ruoyu wang
Author-email: wangkang@139.com
License: UNKNOWN
Platform: UNKNOWN
Classifier: Programming Language :: Python :: 3
Classifier: License :: OSI Approved :: MIT License
Classifier: Operating System :: OS Independent
